charon/__init__.py
charon/argparser/__init__.py
charon/argparser/parser.py
charon/colors/__init__.py
charon/colors/color_dat.py
charon/pgbar/__init__.py
charon/pgbar/bar.py
charon/pgbar/bar_modules.py
charon_jb-0.2.1.dist-info/LICENSE
charon_jb-0.2.1.dist-info/METADATA
charon_jb-0.2.1.dist-info/WHEEL
charon_jb-0.2.1.dist-info/top_level.txt
charon_jb-0.2.1.dist-info/RECORD
